logging_format/__init__.py
logging_format/api.py
logging_format/violations.py
logging_format/visitor.py
logging_format/whitelist.py
flake8_logging_format-2024.24.12.dist-info/LICENSE
flake8_logging_format-2024.24.12.dist-info/METADATA
flake8_logging_format-2024.24.12.dist-info/WHEEL
flake8_logging_format-2024.24.12.dist-info/entry_points.txt
flake8_logging_format-2024.24.12.dist-info/top_level.txt
flake8_logging_format-2024.24.12.dist-info/RECORD
