Metadata-Version: 2.1
Name: flake8-logging-format
Version: 2024.24.12
Home-page: https://github.com/globality-corp/flake8-logging-format
Author: Globality Engineering
Author-email: engineering@globality.com
License: Apache License 2.0
Keywords: microcosm
Classifier: Framework :: Flake8
License-File: LICENSE
Provides-Extra: lint
Requires-Dist: flake8 ; extra == 'lint'
Provides-Extra: test
Requires-Dist: pytest ; extra == 'test'
Requires-Dist: pytest-cov ; extra == 'test'
Requires-Dist: PyHamcrest ; extra == 'test'
